{
  "titleSource":
  [
    {
      "image": "http://oz79w3awk.bkt.clouddn.com/2.jpg",
      "title": "8大自考前景最好的专业，有你想学的吗?",
      "subtitle":"选专业是个技术活，不仅要考虑未来就业",
      "link":"http://mp.weixin.qq.com/s/wiSYgE9WIw1BjsFgFP9hxw"
    },
    {
      "image": "http://7xq720.com1.z0.glb.clouddn.com/0762093864174.jpg",
      "title": "donghanlin帅",
      "subtitle":"特朗普发了一条推特，用“incredible”形容欢迎仪式不可思议，还用了“memorable”（难忘的）和“impressive”（印象深刻的）为三军仪仗队点赞！",
      "link":"http://mp.weixin.qq.com/s/UU0fLF3aVPwepaF1oYr3Lw"
    },
    {
      "image":"http://img5.imgtn.bdimg.com/it/u=972572471,3961298188&fm=27&gp=0.jpg",
      "title":"我是第二个描述",
      "subtitle":"特朗普发了一条推特，用“incredible”形容欢迎仪式不可思议，还用了“memorable”（难忘的）和“impressive”（印象深刻的）为三军仪仗队点赞！",
      "link":"http://www.91ld.cn/212/FJ/mb/d7rvAS/index.html"
    },
    {
      "image": "http://img4.imgtn.bdimg.com/it/u=3610011497,275335211&fm=27&gp=0.jpg",
      "title": "嘻嘻，快到碗里来快到碗里来快到碗里来快到碗里来快到碗里来！(4)",
      "subtitle":"11月9日，三军礼兵列阵，枪刺如林。在人民大会堂东门外广场，国家主席习近平举行仪式欢迎美国总统特朗普访华，两国元首共同检阅了中国人民解放军三军仪仗队。",
      "link":"http://www.91ld.cn/212/FJ/mb/d7rvAS/index.html"
    },
    {
      "image":"http://img0.imgtn.bdimg.com/it/u=246623354,2688743770&fm=27&gp=0.jpg",
      "title":"我是第二个描述",
      "subtitle":"在随后举行的会谈中，特朗普总统用了这样一句话赞誉三军仪仗队——“今天上午仪仗队非常精彩，全世界都看了，我已经接到世界各地的朋友的电话，他们都看了，真的是很美，再一次非常感谢您的热情欢迎。",
      "link":"http://www.91ld.cn/212/FJ/mb/d7rvAS/index.html"

    },
    {
      "image": "http://img4.imgtn.bdimg.com/it/u=3610011497,275335211&fm=27&gp=0.jpg",
      "title": "嘻嘻，快到碗里来快到碗里来快到碗里来快到碗里来快到碗里来！(4)",
      "subtitle":"11月9日，三军礼兵列阵，枪刺如林。在人民大会堂东门外广场，国家主席习近平举行仪式欢迎美国总统特朗普访华，两国元首共同检阅了中国人民解放军三军仪仗队。",
      "link":"http://www.91ld.cn/212/FJ/mb/d7rvAS/index.html"
    },
    {
      "image":"http://img0.imgtn.bdimg.com/it/u=246623354,2688743770&fm=27&gp=0.jpg",
      "title":"我是第二个描述",
      "subtitle":"在随后举行的会谈中，特朗普总统用了这样一句话赞誉三军仪仗队——“今天上午仪仗队非常精彩，全世界都看了，我已经接到世界各地的朋友的电话，他们都看了，真的是很美，再一次非常感谢您的热情欢迎。",
      "link":"http://www.91ld.cn/212/FJ/mb/d7rvAS/index.html"

    },
    {
    "image": "http://img4.imgtn.bdimg.com/it/u=3610011497,275335211&fm=27&gp=0.jpg",
    "title": "嘻嘻，快到碗里来快到碗里来快到碗里来快到碗里来快到碗里来！(4)",
    "subtitle":"11月9日，三军礼兵列阵，枪刺如林。在人民大会堂东门外广场，国家主席习近平举行仪式欢迎美国总统特朗普访华，两国元首共同检阅了中国人民解放军三军仪仗队。",
    "link":"http://www.91ld.cn/212/FJ/mb/d7rvAS/index.html"
  },
    {
      "image":"http://img0.imgtn.bdimg.com/it/u=246623354,2688743770&fm=27&gp=0.jpg",
      "title":"我是第二个描述",
      "subtitle":"在随后举行的会谈中，特朗普总统用了这样一句话赞誉三军仪仗队——“今天上午仪仗队非常精彩，全世界都看了，我已经接到世界各地的朋友的电话，他们都看了，真的是很美，再一次非常感谢您的热情欢迎。",
      "link":"http://www.91ld.cn/212/FJ/mb/d7rvAS/index.html"

    },
    {
      "image":"http://img1.imgtn.bdimg.com/it/u=1480548305,2679988160&fm=27&gp=0.jpg",
      "title":"我是第3个描述",
      "subtitle":"特朗普发了一条推特，用“incredible”形容欢迎仪式不可思议，还用了“memorable”（难忘的）和“impressive”（印象深刻的）为三军仪仗队点赞！",
      "link":"http://www.91ld.cn/212/FJ/mb/d7rvAS/index.html"
    }
  ]
}
